{
  "version": "fortress_in_gorge_city_location_v1",
  "location_id": "fortress_in_gorge",
  "name_ru": "Крепость в ущелье",
  "location_type": "city_like",
  "description": "Крепость отделяет полуостров с городом Селдар и стартовыми локациями от внутренних локаций материка. Со стороны материка она серьёзно укреплена.",
  "places": {
    "courtyard": {
      "name_ru": "Внутренний двор",
      "description": "Главная точка крепости, откуда можно попасть во все остальные места.",
      "buttons": [
        "Крепостная Ратуша",
        "Переулки",
        "Застава Искателей",
        "Вернуться на дорогу в город",
        "Выйти за ворота"
      ]
    },
    "town_hall": {
      "name_ru": "Крепостная ратуша",
      "npcs": {
        "manager": {
          "name_ru": "Управляющий",
          "features": [
            "оплата долгов, если игроку закрыт доступ в город",
            "выдача перенаправленных городских наград позже"
          ]
        },
        "commandant": {
          "name_ru": "Комендант Крепости",
          "features": [
            "награды за вклад в защиту от волны монстров позже",
            "особые квесты позже"
          ]
        }
      }
    },
    "alleys": {
      "name_ru": "Переулки",
      "npcs": {
        "resource_buyer": {
          "name_ru": "Скупщик ресурсов",
          "buy_discount_percent_from_base": 30,
          "status": "runtime_later"
        },
        "coordinator": {
          "name_ru": "Координатор",
          "features": [
            "доска заказов на убийства игроков",
            "особые квесты позже",
            "скрытая Гильдия Убийц позже"
          ]
        }
      }
    },
    "seeker_outpost": {
      "name_ru": "Застава Искателей",
      "features": [
        "Доска объявлений для заказов на добычу ресурсов позже",
        "Агент Гильдии для рейдов позже",
        "Найм позже"
      ]
    },
    "road_to_city": {
      "name_ru": "Вернуться на дорогу в город",
      "description": "Возвращает к выбору стартовых локаций / воротам Селдара."
    },
    "mainland_gate": {
      "name_ru": "Выйти за ворота",
      "description": "Отправляет за ворота крепости к будущим внешним локациям материка."
    }
  },
  "coordinator": {
    "menu_buttons": [
      "Доска заказов",
      "Квесты",
      "Гильдия Убийц"
    ],
    "order_board_buttons": [
      "Выставить заказ",
      "Посмотреть заказы",
      "Мои заказы",
      "Взятые заказы",
      "Внутренний двор"
    ],
    "order_form_fields": [
      "Ник игрока",
      "Сколько раз убить игрока",
      "Цена за 1 убийство игрока",
      "Сколько Игроков могут взять этот заказ",
      "Сколько действует заказ",
      "Анонимность заказчика"
    ],
    "hour_cost_copper": 50,
    "anonymous_hour_cost_copper": 200,
    "order_cost_formula": "(price_per_kill * kill_count) + (hour_cost * duration_hours)",
    "evidence_item_id": "evidence_bag"
  }
}