{
  "pack_id": "seldar_market_and_ammo_assets_corrected",
  "version": "2026-05-23",
  "background": "transparent_alpha_after_processing",
  "asset_size": "1024x1024 PNG",
  "items_count": 25,
  "items": [
    {
      "id": "simple_healing_potion",
      "name_ru": "Простое зелье лечения",
      "category": "seldar_market",
      "image": "assets/items/seldar_market/simple_healing_potion.png",
      "source_pack": "Архив ZIP - WinRAR (3).zip",
      "processing": "background_removed_centered_1024_png"
    },
    {
      "id": "mining_pickaxe",
      "name_ru": "Шахтёрская кирка",
      "category": "seldar_market",
      "image": "assets/items/seldar_market/mining_pickaxe.png",
      "source_pack": "Архив ZIP - WinRAR (3).zip",
      "processing": "background_removed_centered_1024_png"
    },
    {
      "id": "woodcutters_axe",
      "name_ru": "Топор дровосека",
      "category": "seldar_market",
      "image": "assets/items/seldar_market/woodcutters_axe.png",
      "source_pack": "Архив ZIP - WinRAR (3).zip",
      "processing": "background_removed_centered_1024_png"
    },
    {
      "id": "ordinary_leather_helmet",
      "name_ru": "Обычный кожаный шлем",
      "category": "seldar_market",
      "image": "assets/items/seldar_market/ordinary_leather_helmet.png",
      "source_pack": "Архив ZIP - WinRAR (3).zip",
      "processing": "background_removed_centered_1024_png"
    },
    {
      "id": "ordinary_leather_chest",
      "name_ru": "Обычный кожаный нагрудник",
      "category": "seldar_market",
      "image": "assets/items/seldar_market/ordinary_leather_chest.png",
      "source_pack": "Архив ZIP - WinRAR (3).zip",
      "processing": "background_removed_centered_1024_png"
    },
    {
      "id": "ordinary_leather_boots",
      "name_ru": "Обычные кожаные ботинки",
      "category": "seldar_market",
      "image": "assets/items/seldar_market/ordinary_leather_boots.png",
      "source_pack": "Архив ZIP - WinRAR (3).zip",
      "processing": "background_removed_centered_1024_png"
    },
    {
      "id": "ordinary_leather_gloves",
      "name_ru": "Обычные кожаные перчатки",
      "category": "seldar_market",
      "image": "assets/items/seldar_market/ordinary_leather_gloves.png",
      "source_pack": "Архив ZIP - WinRAR (3).zip",
      "processing": "background_removed_centered_1024_png"
    },
    {
      "id": "ordinary_leather_belt",
      "name_ru": "Обычный кожаный пояс",
      "category": "seldar_market",
      "image": "assets/items/seldar_market/ordinary_leather_belt.png",
      "source_pack": "Архив ZIP - WinRAR (3).zip",
      "processing": "background_removed_centered_1024_png"
    },
    {
      "id": "ordinary_leather_pants",
      "name_ru": "Обычные кожаные штаны",
      "category": "seldar_market",
      "image": "assets/items/seldar_market/ordinary_leather_pants.png",
      "source_pack": "Архив ZIP - WinRAR (3).zip",
      "processing": "background_removed_centered_1024_png"
    },
    {
      "id": "glass_diamond",
      "name_ru": "Стекляшки: Алмаз",
      "category": "seldar_market",
      "image": "assets/items/seldar_market/glass_diamond.png",
      "source_pack": "Архив ZIP - WinRAR (3).zip",
      "processing": "background_removed_centered_1024_png"
    },
    {
      "id": "glass_ruby",
      "name_ru": "Стекляшки: Рубин",
      "category": "seldar_market",
      "image": "assets/items/seldar_market/glass_ruby.png",
      "source_pack": "Архив ZIP - WinRAR (3).zip",
      "processing": "background_removed_centered_1024_png"
    },
    {
      "id": "glass_sapphire",
      "name_ru": "Стекляшки: Сапфир",
      "category": "seldar_market",
      "image": "assets/items/seldar_market/glass_sapphire.png",
      "source_pack": "Архив ZIP - WinRAR (3).zip",
      "processing": "background_removed_centered_1024_png"
    },
    {
      "id": "glass_emerald",
      "name_ru": "Стекляшки: Изумруд",
      "category": "seldar_market",
      "image": "assets/items/seldar_market/glass_emerald.png",
      "source_pack": "Архив ZIP - WinRAR (3).zip",
      "processing": "background_removed_centered_1024_png"
    },
    {
      "id": "glass_aquamarine",
      "name_ru": "Стекляшки: Аквамарин",
      "category": "seldar_market",
      "image": "assets/items/seldar_market/glass_aquamarine.png",
      "source_pack": "Архив ZIP - WinRAR (3).zip",
      "processing": "background_removed_centered_1024_png"
    },
    {
      "id": "glass_topaz",
      "name_ru": "Стекляшки: Топаз",
      "category": "seldar_market",
      "image": "assets/items/seldar_market/glass_topaz.png",
      "source_pack": "Архив ZIP - WinRAR (3).zip",
      "processing": "background_removed_centered_1024_png"
    },
    {
      "id": "glass_amethyst",
      "name_ru": "Стекляшки: Аметист",
      "category": "seldar_market",
      "image": "assets/items/seldar_market/glass_amethyst.png",
      "source_pack": "Архив ZIP - WinRAR (3).zip",
      "processing": "background_removed_centered_1024_png"
    },
    {
      "id": "arrow_quiver_empty",
      "name_ru": "Пустой колчан для стрел лука",
      "category": "ammunition_quiver",
      "image": "assets/items/ammo/arrow_quiver_empty.png",
      "source_pack": "Архив ZIP - WinRAR (3).zip",
      "processing": "background_removed_centered_1024_png"
    },
    {
      "id": "bolt_quiver_empty",
      "name_ru": "Пустой колчан для болтов арбалета",
      "category": "ammunition_quiver",
      "image": "assets/items/ammo/bolt_quiver_empty.png",
      "source_pack": "Архив ZIP - WinRAR (3).zip",
      "processing": "background_removed_centered_1024_png"
    },
    {
      "id": "arrow_for_bow",
      "name_ru": "Стрела для лука",
      "category": "ammunition_quiver",
      "image": "assets/items/ammo/arrow_for_bow.png",
      "source_pack": "Архив ZIP - WinRAR (3).zip",
      "processing": "background_removed_centered_1024_png"
    },
    {
      "id": "bolt_for_crossbow",
      "name_ru": "Болт для арбалета",
      "category": "ammunition_quiver",
      "image": "assets/items/ammo/bolt_for_crossbow.png",
      "source_pack": "Архив ZIP - WinRAR (3).zip",
      "processing": "background_removed_centered_1024_png"
    },
    {
      "id": "copper_coin",
      "name_ru": "Медная монета",
      "category": "currency",
      "image": "assets/items/currency/copper_coin.png",
      "source_pack": "Архив ZIP - WinRAR (3).zip",
      "processing": "background_removed_centered_1024_png"
    },
    {
      "id": "silver_coin",
      "name_ru": "Серебряная монета",
      "category": "currency",
      "image": "assets/items/currency/silver_coin.png",
      "source_pack": "Архив ZIP - WinRAR (3).zip",
      "processing": "background_removed_centered_1024_png"
    },
    {
      "id": "gold_coin",
      "name_ru": "Золотая монета",
      "category": "currency",
      "image": "assets/items/currency/gold_coin.png",
      "source_pack": "Архив ZIP - WinRAR (3).zip",
      "processing": "background_removed_centered_1024_png"
    },
    {
      "id": "magic_gold_coin",
      "name_ru": "Магическое золото",
      "category": "currency",
      "image": "assets/items/currency/magic_gold_coin.png",
      "source_pack": "Архив ZIP - WinRAR (3).zip",
      "processing": "background_removed_centered_1024_png"
    },
    {
      "id": "ancient_coin",
      "name_ru": "Древняя монета",
      "category": "currency",
      "image": "assets/items/currency/ancient_coin.png",
      "source_pack": "Архив ZIP - WinRAR (3).zip",
      "processing": "background_removed_centered_1024_png"
    }
  ]
}